ytx/__init__.py
ytx/audio.py
ytx/cache.py
ytx/chapters.py
ytx/chunking.py
ytx/cli.py
ytx/config.py
ytx/downloader.py
ytx/errors.py
ytx/logging.py
ytx/models.py
ytx/stitch.py
ytx/summarizer.py
ytx/engines/__init__.py
ytx/engines/base.py
ytx/engines/cloud_base.py
ytx/engines/deepgram_engine.py
ytx/engines/eleven_engine.py
ytx/engines/gemini_engine.py
ytx/engines/openai_engine.py
ytx/engines/whisper_engine.py
ytx/engines/whispercpp_engine.py
ytx/exporters/__init__.py
ytx/exporters/base.py
ytx/exporters/json_exporter.py
ytx/exporters/manager.py
ytx/exporters/markdown_exporter.py
ytx/exporters/srt_exporter.py
ytx/exporters/utils.py
tubescribe-0.3.6.dist-info/METADATA
tubescribe-0.3.6.dist-info/WHEEL
tubescribe-0.3.6.dist-info/entry_points.txt
tubescribe-0.3.6.dist-info/RECORD
