Metadata-Version: 2.4
Name: tubescribe
Version: 0.3.6
Summary: CLI to transcribe YouTube audio via Whisper (local) or Gemini (cloud)
Project-URL: Homepage, https://github.com/prateekjain24/TubeScribe
Project-URL: Repository, https://github.com/prateekjain24/TubeScribe
Project-URL: Issues, https://github.com/prateekjain24/TubeScribe/issues
Author-email: Prateek <19404752+prateekjain24@users.noreply.github.com>
Keywords: caption,cli,speech-to-text,srt,transcription,whisper,youtube
Classifier: Development Status :: 4 - Beta
Classifier: Environment :: Console
Classifier: Intended Audience :: Developers
Classifier: Intended Audience :: End Users/Desktop
Classifier: License :: OSI Approved :: MIT License
Classifier: Programming Language :: Python
Classifier: Programming Language :: Python :: 3
Classifier: Programming Language :: Python :: 3 :: Only
Classifier: Programming Language :: Python :: 3.10
Classifier: Programming Language :: Python :: 3.11
Classifier: Programming Language :: Python :: 3.12
Classifier: Programming Language :: Python :: 3.13
Classifier: Topic :: Multimedia :: Sound/Audio
Classifier: Topic :: Multimedia :: Video
Classifier: Topic :: Utilities
Requires-Python: >=3.10
Requires-Dist: faster-whisper>=1.2.0
Requires-Dist: google-generativeai>=0.7.2
Requires-Dist: httpx>=0.28.1
Requires-Dist: orjson>=3.11.3
Requires-Dist: pydantic-settings>=2.8.1
Requires-Dist: pydantic>=2.10.6
Requires-Dist: python-dotenv>=1.0.1
Requires-Dist: rich>=13.9.4
Requires-Dist: srt>=3.5.3
Requires-Dist: tenacity>=9.1.2
Requires-Dist: typer>=0.15.2
Requires-Dist: yt-dlp>=2025.9.5
Provides-Extra: deepgram
Requires-Dist: deepgram-sdk>=2.0.0; extra == 'deepgram'
Provides-Extra: openai
Requires-Dist: openai>=1.0.0; extra == 'openai'
